mempass/__init__.py
mempass/command_line.py
mempass/password_generator.py
mempass/tests.py
mempass-0.1.2.dist-info/LICENSE
mempass-0.1.2.dist-info/METADATA
mempass-0.1.2.dist-info/WHEEL
mempass-0.1.2.dist-info/entry_points.txt
mempass-0.1.2.dist-info/top_level.txt
mempass-0.1.2.dist-info/RECORD
